<?xml version="1.0" encoding="UTF-8"?>
<meta xmlns="http://exist-db.org/xquery/repo" commit-id="8337057d5c3ad2e550b89473ddff2d9de6491578" commit-time="1690335856">
    <description>Visits (data)</description>
    <author>Office of the Historian</author>
    <website>https://history.state.gov</website>
    <status/>
    <license/>
    <copyright/>
    <type>application</type>
    <target>visits</target>
    <prepare>pre-install.xql</prepare>
    <finish/>
    <permissions xmlns:repo="http://exist-db.org/xquery/repo" password="" group="hsg" mode="rw-rw-r--" user="hsg"/>
</meta>